markdown_math_escape/__init__.py
markdown_math_escape/_meta.py
markdown_math_escape/core.py
markdown_math_escape-0.20.12.17.dist-info/LICENSE
markdown_math_escape-0.20.12.17.dist-info/METADATA
markdown_math_escape-0.20.12.17.dist-info/WHEEL
markdown_math_escape-0.20.12.17.dist-info/top_level.txt
markdown_math_escape-0.20.12.17.dist-info/RECORD
