Metadata-Version: 2.1
Name: markdown-math-escape
Version: 0.20.12.17
Summary: Python-Markdown extension to escape math expressions like $2\pi$
Home-page: https://github.com/sgryjp/markdown_math_escape
Author: Suguru Yamamoto
Author-email: sgryjp@gmail.com
License: MIT
Platform: UNKNOWN
Requires-Python: >=3.6
Requires-Dist: Markdown (>=3.1.1)
